Metadata-Version: 1.1
Name: django-urldecorators
Version: 0.7
Summary: Django-urldecorators is a reusable Django application which allows apply view decorators and middleware components depending on requested url.
Home-page: http://github.com/mila/django-urldecorators/tree/master
Author: Miloslav Pojman
Author-email: miloslav.pojman@gmail.com
License: UNKNOWN
Platform: UNKNOWN
Classifier: Environment :: Web Environment
Classifier: Intended Audience :: Developers
Classifier: License :: OSI Approved :: BSD License
Classifier: Operating System :: OS Independent
Classifier: Programming Language :: Python
Classifier: Framework :: Django
